dive/Viz_UI.py
dive/__init__.py
dive/add.png
dive/csv_tocolors.py
dive/helper.py
dive/loading.py
dive/main.py
dive/mask.py
dive/minus.png
dive/showman.py
dive/tract.py
dive_mri-1.0.4.dist-info/LICENSE.txt
dive_mri-1.0.4.dist-info/METADATA
dive_mri-1.0.4.dist-info/WHEEL
dive_mri-1.0.4.dist-info/entry_points.txt
dive_mri-1.0.4.dist-info/top_level.txt
dive_mri-1.0.4.dist-info/RECORD
