Metadata-Version: 2.1
Name: dive-mri
Version: 1.0.4
Summary: The Diffusion Visualization Explorer (DiVE) Tool
License: Unless otherwise specified by LICENSE.txt files in individual
Project-URL: Repository, https://github.com/USC-LoBeS/dive
Keywords: Diffusion MRI,along-tract visualization,tractography,white matter bundle
Classifier: Intended Audience :: Science/Research
Classifier: Programming Language :: Python :: 3
Classifier: Operating System :: OS Independent
Requires-Python: >=3.9
License-File: LICENSE.txt
Requires-Dist: distinctipy>=1.2.3
Requires-Dist: fury>=0.9.0
Requires-Dist: matplotlib
Requires-Dist: nibabel
Requires-Dist: numpy<2.0.0
Requires-Dist: ordered-set
Requires-Dist: pandas
Requires-Dist: pyvista
Requires-Dist: trx-python>0.2.9
Requires-Dist: vtk>=9.3.0
Requires-Dist: webcolors
Requires-Dist: setuptools>=69.5
Requires-Dist: dipy
